rt_generic/__init__.py
rt_generic/py.typed
rt_generic/rt_generic.py
rt_generic/type_setup.py
rt_generic/utils.py
rt_generic/version.py
rt_generic-0.2.4.dist-info/METADATA
rt_generic-0.2.4.dist-info/WHEEL
rt_generic-0.2.4.dist-info/RECORD
