Metadata-Version: 2.4
Name: rt-generic
Version: 0.2.4
Summary: tools to make typing more consistent in older versions of python3, and access generic variables at runtime
Project-URL: repository, https://codeberg.org/Pusher2531/rt-generic.git
Author-email: Doug Sojourner <doug@sojournings.org>
License: GNU General Public License v3 (GPLv3)
Keywords: generic,run time types,runtime,typed,typing
Classifier: Development Status :: 3 - Alpha
Classifier: Intended Audience :: Developers
Classifier: License :: OSI Approved :: GNU General Public License v3 (GPLv3)
Classifier: Natural Language :: English
Classifier: Operating System :: OS Independent
Classifier: Programming Language :: Python :: 3
Classifier: Programming Language :: Python :: 3 :: Only
Classifier: Programming Language :: Python :: 3.7
Classifier: Programming Language :: Python :: 3.8
Classifier: Programming Language :: Python :: 3.9
Classifier: Programming Language :: Python :: 3.10
Classifier: Programming Language :: Python :: 3.11
Classifier: Programming Language :: Python :: 3.12
Classifier: Programming Language :: Python :: 3.13
Classifier: Topic :: Software Development
Classifier: Topic :: Software Development :: Libraries
Classifier: Topic :: Software Development :: Libraries :: Python Modules
Classifier: Typing :: Typed
Requires-Python: <4.0,>=3.7
Requires-Dist: typing-extensions; python_version < '3.11'
